{"trial_id": "0024", "hyperparameters": {"space": [{"class_name": "Choice", "config": {"name": "activation", "default": "relu", "conditions": [], "values": ["relu", "tanh", "selu"], "ordered": false}}, {"class_name": "Int", "config": {"name": "first_units", "default": null, "conditions": [], "min_value": 1, "max_value": 100, "step": 2, "sampling": "linear"}}, {"class_name": "Int", "config": {"name": "num_layers", "default": null, "conditions": [], "min_value": 1, "max_value": 8, "step": 1, "sampling": "linear"}}, {"class_name": "Int", "config": {"name": "units_0", "default": null, "conditions": [], "min_value": 1, "max_value": 100, "step": 2, "sampling": "linear"}}, {"class_name": "Int", "config": {"name": "units_1", "default": null, "conditions": [], "min_value": 1, "max_value": 100, "step": 2, "sampling": "linear"}}, {"class_name": "Int", "config": {"name": "units_2", "default": null, "conditions": [], "min_value": 1, "max_value": 100, "step": 2, "sampling": "linear"}}, {"class_name": "Int", "config": {"name": "units_3", "default": null, "conditions": [], "min_value": 1, "max_value": 100, "step": 2, "sampling": "linear"}}, {"class_name": "Int", "config": {"name": "units_4", "default": null, "conditions": [], "min_value": 1, "max_value": 100, "step": 2, "sampling": "linear"}}, {"class_name": "Int", "config": {"name": "units_5", "default": null, "conditions": [], "min_value": 1, "max_value": 100, "step": 2, "sampling": "linear"}}, {"class_name": "Int", "config": {"name": "units_6", "default": null, "conditions": [], "min_value": 1, "max_value": 100, "step": 2, "sampling": "linear"}}, {"class_name": "Int", "config": {"name": "units_7", "default": null, "conditions": [], "min_value": 1, "max_value": 100, "step": 2, "sampling": "linear"}}], "values": {"activation": "selu", "first_units": 27, "num_layers": 1, "units_0": 43, "units_1": 83, "units_2": 75, "units_3": 91, "units_4": 33, "units_5": 39, "units_6": 81, "units_7": 51, "tuner/epochs": 20, "tuner/initial_epoch": 7, "tuner/bracket": 1, "tuner/round": 1, "tuner/trial_id": "0021"}}, "metrics": {"metrics": {"loss": {"direction": "min", "observations": [{"value": [0.3534792363643646], "step": 0}]}, "accuracy": {"direction": "max", "observations": [{"value": [0.8496122360229492], "step": 0}]}, "val_loss": {"direction": "min", "observations": [{"value": [0.35675305128097534], "step": 0}]}, "val_accuracy": {"direction": "max", "observations": [{"value": [0.8490816354751587], "step": 0}]}}}, "score": 0.8490816354751587, "best_step": 0, "status": "COMPLETED", "message": null}